clickhouse_pool/__init__.py
clickhouse_pool/pool.py
clickhouse_pool-0.6.1.dist-info/LICENSE
clickhouse_pool-0.6.1.dist-info/METADATA
clickhouse_pool-0.6.1.dist-info/WHEEL
clickhouse_pool-0.6.1.dist-info/RECORD
