Metadata-Version: 2.1
Name: clickhouse-pool
Version: 0.6.1
Summary: a thread-safe connection pool for ClickHouse
Home-page: https://ericmccarthy7.github.io/clickhouse-pool/
License: LGPL-3.0-or-later
Author: Eric McCarthy
Author-email: ericmccarthy7@gmail.com
Requires-Python: >=3.9,<4.0
Classifier: License :: OSI Approved :: GNU Lesser General Public License v3 or later (LGPLv3+)
Classifier: Programming Language :: Python :: 3
Classifier: Programming Language :: Python :: 3.9
Classifier: Programming Language :: Python :: 3.10
Classifier: Programming Language :: Python :: 3.11
Classifier: Programming Language :: Python :: 3.12
Requires-Dist: clickhouse-driver (==0.2.7)
Project-URL: Repository, https://github.com/ericmccarthy7/clickhouse-pool
